alibabacloud_pairecservice20221213/__init__.py
alibabacloud_pairecservice20221213/client.py
alibabacloud_pairecservice20221213/models/__init__.py
alibabacloud_pairecservice20221213/models/_apply_engine_config_request.py
alibabacloud_pairecservice20221213/models/_apply_engine_config_response.py
alibabacloud_pairecservice20221213/models/_apply_engine_config_response_body.py
alibabacloud_pairecservice20221213/models/_backflow_feature_consistency_check_job_data_request.py
alibabacloud_pairecservice20221213/models/_backflow_feature_consistency_check_job_data_response.py
alibabacloud_pairecservice20221213/models/_backflow_feature_consistency_check_job_data_response_body.py
alibabacloud_pairecservice20221213/models/_change_recall_management_service_version_request.py
alibabacloud_pairecservice20221213/models/_change_recall_management_service_version_response.py
alibabacloud_pairecservice20221213/models/_change_recall_management_service_version_response_body.py
alibabacloud_pairecservice20221213/models/_check_instance_resources_request.py
alibabacloud_pairecservice20221213/models/_check_instance_resources_response.py
alibabacloud_pairecservice20221213/models/_check_instance_resources_response_body.py
alibabacloud_pairecservice20221213/models/_check_traffic_control_task_expression_request.py
alibabacloud_pairecservice20221213/models/_check_traffic_control_task_expression_response.py
alibabacloud_pairecservice20221213/models/_check_traffic_control_task_expression_response_body.py
alibabacloud_pairecservice20221213/models/_clone_engine_config_request.py
alibabacloud_pairecservice20221213/models/_clone_engine_config_response.py
alibabacloud_pairecservice20221213/models/_clone_engine_config_response_body.py
alibabacloud_pairecservice20221213/models/_clone_experiment_group_request.py
alibabacloud_pairecservice20221213/models/_clone_experiment_group_response.py
alibabacloud_pairecservice20221213/models/_clone_experiment_group_response_body.py
alibabacloud_pairecservice20221213-4.1.0.dist-info/LICENSE
alibabacloud_pairecservice20221213-4.1.0.dist-info/METADATA
alibabacloud_pairecservice20221213-4.1.0.dist-info/WHEEL
alibabacloud_pairecservice20221213-4.1.0.dist-info/top_level.txt
alibabacloud_pairecservice20221213-4.1.0.dist-info/RECORD
